{"about.md":"e5a0c172","devops_frontend_arco-design简单使用记录.md":"089195dd","devops_frontend_eslint和prettier配置.md":"9075fbe8","devops_frontend_前端项目部署方案.md":"3f1ffba4","devops_others_centos分区合并.md":"33da3d90","devops_others_centos挂载硬盘.md":"8350a851","devops_others_express中配置log4js.md":"d406921e","devops_others_github常用api.md":"83a76bf5","devops_others_物理机安装linux同时实现内网穿透.md":"f862ea39","index.md":"2535d9e3","js_designpatterns_event_index.md":"9b92db1d","js_designpatterns_index.md":"de8e61b5","js_designpatterns_mixin_index.md":"6beaaf74","js_designpatterns_module_index.md":"12868c3c","js_designpatterns_observe_index.md":"4f77be70","js_designpatterns_prototype_index.md":"2d2d7989","js_designpatterns_provide_index.md":"6f5d8b70","js_designpatterns_proxy_index.md":"e2c17e4d","js_designpatterns_singleton_index.md":"bf626a65","js_vue_directives_tooltip_index.md":"46a9931f","project_50projects50days_blurryloading.md":"db7242e6","project_50projects50days_calendar.md":"fc508e14","project_50projects50days_dragndrop.md":"eb1a1c36","project_50projects50days_drawingboard.md":"453ab7ef","project_50projects50days_rippleeffect.md":"c953190f","project_50projects50days_morecontexttipanimation.md":"6d6bd605","project_50projects50days_scrollanimation.md":"6e640214","project_50projects50days_soundbtn.md":"ce111d80","project_mr-notice_auto-deploy.md":"e93c7638","project_others_24小时直播推流.md":"27908409","project_others_前端语音识别探索.md":"849c6b27","project_others_家用摄像头本地存储和查看.md":"0a9fe7e8","project_others_生成脚本执行记录并发布npm包.md":"79d85be3","project_others_软路由探索.md":"ca4767f3","project_typescript-study_01-函数间ts的交互使用.md":"f7607f2f","project_typescript-study_02-ts实现函数重载.md":"966ea300","project_typescript-study_03-ts对简单的可选参数处理.md":"447b97f5","project_typescript-study_04-ts中元组的简单使用.md":"903d4906","project_typescript-study_05-ts中泛型的简单使用.md":"92f95c40","project_typescript-study_06-ts练习(reduce).md":"1e0004a5","project_typescript-study_07-ts泛型中的keyof.md":"41b73e6e","project_typescript-study_08-ts中的utility-types.md":"dfd010ff","project_typescript-study_09-ts中的readonly和不可改属性.md":"d137a40a","project_typescript-study_10-ts中的enum和literal.md":"f696f5f1","project_typescript-study_11-ts中class的implement与属性可见性.md":"44b2ad0e","project_typescript-study_12-ts中的mapped types.md":"8a7d6717","project_typescript-study_13-ts中的readonly和static.md":"7c35d1b7","project_typescript-study_14-ts中class的abstract.md":"fb072918","project_typescript-study_15-ts中实现mixin函数.md":"d40a0c7e","project_typescript-study_16-ts中的条件类型.md":"5940b6a5","project_typescript-study_17-ts中的相关操作符.md":"b4fec403","project_typescript-study_home.md":"8cd0a213"}
